surfsci/__about__.py
surfsci/__init__.py
surfsci/utils/__init__.py
surfsci/utils/gpol.py
surfsci/utils/xy_conv.py
surfsci-0.2.0.dist-info/METADATA
surfsci-0.2.0.dist-info/WHEEL
surfsci-0.2.0.dist-info/entry_points.txt
surfsci-0.2.0.dist-info/licenses/LICENSE.txt
surfsci-0.2.0.dist-info/RECORD
