Metadata-Version: 2.4
Name: surfsci
Version: 0.2.0
Summary: A suite of tools for handling surface science related x-ray data
Project-URL: Documentation, https://gitlab.com/ddkn/surfsci#readme
Project-URL: Issues, https://gitlab.com/ddkn/surfsci/issues
Project-URL: Source, https://gitlab.com/ddkn/surfsci
Author-email: David Kalliecharan <david@david.science>
License-Expression: BSD-2-Clause
License-File: LICENSE.txt
Keywords: Surface Science
Classifier: Development Status :: 4 - Beta
Classifier: Programming Language :: Python
Classifier: Programming Language :: Python :: 3.8
Classifier: Programming Language :: Python :: 3.9
Classifier: Programming Language :: Python :: 3.10
Classifier: Programming Language :: Python :: 3.11
Classifier: Programming Language :: Python :: 3.12
Classifier: Programming Language :: Python :: Implementation :: CPython
Classifier: Programming Language :: Python :: Implementation :: PyPy
Classifier: Topic :: Scientific/Engineering :: Chemistry
Classifier: Topic :: Scientific/Engineering :: Physics
Requires-Python: >=3.8
Requires-Dist: xps
